Workbook

Sheet BOM
A1: Subsystem | B1: Component | C1: Exact part / spec | D1: Qty | E1: Unit cost (INR) | F1: Line total (INR, formula) | G1: Est. (INR) - ESTIMATE range | H1: Vendor | I1: Vendor city | J1: Sourcing flag | K1: Lead time (days) | L1: Product URL | M1: Alt vendor | N1: Notes | O1: Price evidence | P1: Checked on | Q1: Est. low (INR) | R1: Est. high (INR)
A2: Edge Node | B2: Raspberry Pi 5 8GB | C2: Raspberry Pi 5 Model B, BCM2712, 8GB LPDDR4X | D2: 1 | E2: 22499 | F2: =IF(ISNUMBER(E2),D2*E2,0) -> 22499 | H2: Probots (Probots Technologies) | I2: Bengaluru (Nagarbhavi; contact page) | J2: Domestic | K2: 4 | L2: https://probots.co.in/raspberry-pi-5-model-b-bcm2712-arm-cortex-a76-8gb-ram-2-4ghz-single-board-computer.html | M2: Robocraze, Bengaluru: Rs 19,999 incl GST (SOLD OUT 24-Oct) https://robocraze.com/products/raspberry-pi-5-8gb ; element14 India Rs 16,717.93 (GST n/s, ships from SG/UK stock, 3-6 business days - IMPORTED shipment) | N2: Listed Rs 22,499.00 incl GST. In stock. Approved-reseller status of Probots not verified. Hubtronics (Rs 20,765) rejected: Pune. | O2: Product page | P2: 2026-10-25 | Q2: 0 | R2: 0
A3: Edge Node | B3: Raspberry Pi AI HAT+ 26 TOPS | C3: Raspberry Pi AI HAT+ (Hailo-8, 26 TOPS), PCIe Gen3 x1 | D3: 1 | E3: 14999 | F3: =IF(ISNUMBER(E3),D3*E3,0) -> 14999 | H3: Probots (Probots Technologies) | I3: Bengaluru (Nagarbhavi; contact page) | J3: Domestic | K3: 4 | L3: https://probots.co.in/official-raspberry-pi-ai-hat-26-tops.html | M3: Robocraze, Bengaluru: Rs 11,309 incl GST (SOLD OUT 24-Oct) https://robocraze.com/products/official-raspberry-pi-ai-hat-26-tops | N3: Listed Rs 14,999.00 incl GST. In stock. Hubtronics (Rs 10,989, OOS) rejected: Pune. Uses the Pi 5's only PCIe lane, so boot media is microSD (no NVMe). | O3: Product page | P3: 2026-10-25 | Q3: 0 | R3: 0
A4: Edge Node | B4: Active cooler | C4: Official Raspberry Pi 5 Active Cooler (heatsink + PWM fan) | D4: 1 | E4: 749 | F4: =IF(ISNUMBER(E4),D4*E4,0) -> 749 | H4: Probots (Probots Technologies) | I4: Bengaluru (Nagarbhavi; contact page) | J4: Domestic | K4: 4 | L4: https://probots.co.in/official-raspberry-pi-5-active-cooler-heatsink-fan.html | M4: No 2nd allowed-city vendor verified (Hubtronics Rs 560 is Pune) | N4: Listed Rs 749.00 incl GST. In stock. Design note (25 Oct): sits inside the sealed box and circulates the internal air; it does not remove heat from the box (CALCS section 5). | O4: Product page | P4: 2026-10-25 | Q4: 0 | R4: 0
A5: Edge Node | B5: microSD card 128GB | C5: SanDisk 128GB microSDXC (A1/A2 class to confirm at checkout) | D5: 1 | E5: 2725 | F5: =IF(ISNUMBER(E5),D5*E5,0) -> 2725 | H5: Robocraze (TIF Labs Pvt Ltd) | I5: Bengaluru (Kalyan Nagar warehouse; contact page) | J5: Domestic | K5: 4 | L5: https://robocraze.com/search?q=sandisk | M5: Robocraze SanDisk Extreme 128GB A2 Rs 3,643 (sold out) | N5: Listed Rs 2,725.00 incl GST. Shown as add-to-cart on search page; >=64GB requirement met. | O5: Store/category listing page | P5: 2026-10-24 | Q5: 0 | R5: 0
A6: Edge Node | B6: USB-C PSU (bench / commissioning) | C6: Raspberry Pi 27W USB-C PSU 5.1V 5A, white, IN plug | D6: 1 | E6: 1749 | F6: =IF(ISNUMBER(E6),D6*E6,0) -> 1749 | H6: Probots (Probots Technologies) | I6: Bengaluru (Nagarbhavi; contact page) | J6: Domestic | K6: 4 | L6: https://probots.co.in/raspberry-pi-27w-usb-c-power-supply-white-in-plug.html | M6: Robocraze: Rs 1,254 (white) on search page, stock not shown | N6: Listed Rs 1,749.00 incl GST. In stock. Bench use; in the enclosure the Pi is fed by the 24V->5V buck below. | O6: Product page | P6: 2026-10-25 | Q6: 0 | R6: 0
A7: Edge Node | B7: 24V->5.1V 5A buck (Pi 5 feed in enclosure) | C7: XL4015 step-down, 4-38V in, 1.25-36V out, 5A max | D7: 1 | E7: 299 | F7: =IF(ISNUMBER(E7),D7*E7,0) -> 299 | H7: Probots (Probots Technologies) | I7: Bengaluru (Nagarbhavi; contact page) | J7: Domestic | K7: 4 | L7: https://probots.co.in/xl4015-step-down-buck-converter-adjustable-max-output-36v-5a.html | M7: Thingbits / Robocraze equivalents (not priced) | N7: Listed Rs 299.00 incl GST. In stock. 5A is the module's max: derate and add heatsink, target to be bench-verified. A Mean Well DC-DC 5V module would be the industrial option (quote). | O7: Product page | P7: 2026-10-25 | Q7: 0 | R7: 0
A8: Edge Node | B8: Pi 5 UPS module (>=10 min ride-through) | C8: Geekworm X1202 UPS HAT for Raspberry Pi 5 (18650 based, 5.1 V 5 A output) | D8: 1 | E8: quote needed | F8: =IF(ISNUMBER(E8),D8*E8,0) -> 0 | G8: 4,599-4,599 (line) | H8: Probots (Probots Technologies) | I8: Bengaluru (Nagarbhavi; contact page) | J8: Domestic | K8: 4 | L8: https://probots.co.in/metal-case-raspberry-pi-5-x1202-ups-board.html | M8: Geekworm X1202 (Robu.in - Pune, rejected); quote from Robocraze/Thingbits | N8: 25-Oct: the 24-Oct figure of Rs 4,599 came from a related-products block and was labelled 'Waveshare'. The Probots page checked on 25-Oct is the Geekworm X1202-C1 metal case at Rs 2,649 incl GST (in stock); it does not show a Rs 4,599 UPS board. Rs 4,599 is kept only as the budget placeholder until a quote or the board's own product page is seen. Geekworm sells the X1202 as a 4-cell board; Probots says 2 cells. UPS covers the Pi only (not the PoE switch or camera). Ride-through time is a target, to be bench-verified. Limitation (25 Oct): the PoE switch and camera have no UPS, so ANPR is lost on a mains outage while the Pi and RFID reader keep running (docs/OPEN_DECISIONS.md D3). | O8: ESTIMATE - quote needed | P8: 2026-10-25 | Q8: 4599 | R8: 4599
A9: Edge Node | B9: 18650 Li-ion cells for UPS module | C9: Protected 18650, 2500-3000 mAh (2 per Probots X1202 page; Geekworm describes a 4-cell board: confirm count) | D9: 2 | E9: quote needed | F9: =IF(ISNUMBER(E9),D9*E9,0) -> 0 | G9: 500-900 (line) | H9: Probots (Probots Technologies) | I9: Bengaluru (Nagarbhavi; contact page) | J9: Domestic | K9: 7 | M9: Thingbits, Mumbai | N9: Not priced: quote needed. | O9: ESTIMATE - quote needed | P9: 2026-10-24 | Q9: 500 | R9: 900
A10: Edge Node | B10: SUBTOTAL - Edge Node | F10: =SUM(F2:F9) -> 43020 | K10: =MAX(K2:K9) -> 7 | Q10: =SUM(Q2:Q9) -> 5099 | R10: =SUM(R2:R9) -> 5499
A12: Lane Controller PCB | B12: MCU module | C12: Espressif ESP32-S3-WROOM-1-N16R8 (16MB flash, 8MB PSRAM) | D12: 2 | E12: 1010.63 | F12: =IF(ISNUMBER(E12),D12*E12,0) -> 2021.26 | H12: LionCircuits | I12: Bengaluru (080 phone; Karnataka facility) - address not on site, confirm | J12: Domestic | K12: 10 | L12: https://lioncircuits.com/parts/ESP32-S3-WROOM-1-N16R8 | M12: Probots ESP32-S3 N16R8 dev board Rs 1,299 incl GST (bench firmware) https://probots.co.in/esp32-s3-wroom-1-n16r8-development-board-wireless-module-wifi-bluetooth.html | N12: Listed Rs 856.47; GST not stated, +18% applied (conservative). Qty 1 + 1 spare. Ships in 7-10 days (stated). Page text says '6MB Quad SPI', confirm flash size. | O12: Product page | P12: 2026-10-25 | Q12: 0 | R12: 0
A13: Lane Controller PCB | B13: RS485 transceiver | C13: Maxim MAX3485ESA+T, 3.3V, SOIC-8, 10 Mbps | D13: 0 | E13: 1100.09 | F13: =IF(ISNUMBER(E13),D13*E13,0) -> 0 | H13: LionCircuits | I13: Bengaluru (080 phone; Karnataka facility) - address not on site, confirm | J13: Domestic | K13: 10 | L13: https://lioncircuits.com/parts/MAX3485ESA+T | M13: Probots UART TTL-RS485 auto-flow module PRO2056 Rs 399 incl GST https://probots.co.in/uart-ttl-to-rs485-serial-converter.html | N13: SUPERSEDED 25 Oct: the schematic uses TI THVD1450DR (see the line 'Schematic parts not otherwise listed'). Qty set to 0; the priced MAX3485ESA is kept visible for reference only. Original note: Listed Rs 932.28; GST not stated, +18% applied (conservative). Qty 1 + 1 spare. Ships in 7-10 days (stated). | O13: Product page | P13: 2026-10-24 | Q13: 0 | R13: 0
A14: Lane Controller PCB | B14: RS485 TVS | C14: Semtech SM712.TCT, asymmetric 12V/7V TVS, SOT-23, 400W | D14: 2 | E14: 196.53 | F14: =IF(ISNUMBER(E14),D14*E14,0) -> 393.06 | H14: LionCircuits | I14: Bengaluru (080 phone; Karnataka facility) - address not on site, confirm | J14: Domestic | K14: 10 | L14: https://lioncircuits.com/parts/SM712.TCT | N14: Listed Rs 166.55; GST not stated, +18% applied (conservative). Ships in 7-10 days (stated). | O14: Product page | P14: 2026-10-24 | Q14: 0 | R14: 0
A15: Lane Controller PCB | B15: H-bridge motor driver | C15: BTS7960 43A dual half-bridge module (IBT-2) | D15: 1 | E15: 699 | F15: =IF(ISNUMBER(E15),D15*E15,0) -> 699 | H15: Probots (Probots Technologies) | I15: Bengaluru (Nagarbhavi; contact page) | J15: Domestic | K15: 4 | L15: https://probots.co.in/bts7960-43a-stepper-motor-driver-h-bridge-high-power-module-motor-control.html | M15: Thingbits, Mumbai: Rs 251.34 incl GST (SOLD OUT) https://www.thingbits.in/products/bts7960-43a-h-bridge-motor-driver | N15: Listed Rs 699.00 incl GST. In stock. ONE DESIGN (25 Oct): the schematic now uses this IBT-2 module (2x BTS7960, 5.5-27 V motor supply, so 24 V is inside its range; the former BTN8982TA pair is gone). Only its 8 logic pins reach the PCB (header J14); the module's B+/B-/M+/M- terminals are wired directly: contactor K1 contacts -> B+/B-, motor -> M+/M-. Add 470 uF 50 V + SMCJ28A across B+/B- at the module (in the misc line). Logic is 5 V (on-board buffer); the PCB level-shifts with 74AHCT1G08. Module IS pins have a 1k to GND each. Thingbits Mumbai Rs 251.34 was sold out. | O15: Product page | P15: 2026-10-25 | Q15: 0 | R15: 0
A16: Lane Controller PCB | B16: 24V->5V buck (logic rail) | C16: XL4015 step-down, 5A max | D16: 0 | E16: 299 | F16: =IF(ISNUMBER(E16),D16*E16,0) -> 0 | H16: Probots (Probots Technologies) | I16: Bengaluru (Nagarbhavi; contact page) | J16: Domestic | K16: 4 | L16: https://probots.co.in/xl4015-step-down-buck-converter-adjustable-max-output-36v-5a.html | N16: SUPERSEDED 25 Oct: the schematic uses a TPS54560BDDA 5 A buck on the PCB (parts in the line 'Schematic parts not otherwise listed'). Qty set to 0. The XL4015 modules on the P10 and Edge lines are separate. Original note: Listed Rs 299.00 incl GST. In stock. | O16: Product page | P16: 2026-10-25 | Q16: 0 | R16: 0
A17: Lane Controller PCB | B17: 3.3V regulator | C17: Diodes AP2112K-3.3TRG1 LDO 600mA SOT-23-5 | D17: 0 | E17: 21.33 | F17: =IF(ISNUMBER(E17),D17*E17,0) -> 0 | H17: LionCircuits | I17: Bengaluru (080 phone; Karnataka facility) - address not on site, confirm | J17: Domestic | K17: 10 | L17: https://lioncircuits.com/parts/AP2112K-3.3TRG1 | N17: SUPERSEDED 25 Oct: the schematic uses a TLV62569DBVR 2 A buck (the 600 mA LDO was marginal for ESP32-S3 Wi-Fi peaks). Qty set to 0. Original note: Listed Rs 18.08; GST not stated, +18% applied (conservative). Lowest tier is 10 pcs. 600mA is tight for ESP32-S3 Wi-Fi peaks: bench-verify, or switch to a 1A LDO. | O17: Product page | P17: 2026-10-24 | Q17: 0 | R17: 0
A18: Lane Controller PCB | B18: Optocouplers | C18: PC817C 4-SMD (limit switches, photo-beam, E-stop sense) | D18: 10 | E18: 4.24 | F18: =IF(ISNUMBER(E18),D18*E18,0) -> 42.4 | H18: LionCircuits | I18: Bengaluru (080 phone; Karnataka facility) - address not on site, confirm | J18: Domestic | K18: 10 | L18: https://lioncircuits.com/parts/PC817C | N18: Listed Rs 3.59; GST not stated, +18% applied (conservative). | O18: Product page | P18: 2026-10-24 | Q18: 0 | R18: 0
A19: Lane Controller PCB | B19: Screw terminals | C19: 2-pin fixed screw terminal block, 5.08mm pitch | D19: 12 | E19: 15 | F19: =IF(ISNUMBER(E19),D19*E19,0) -> 180 | H19: Probots (Probots Technologies) | I19: Bengaluru (Nagarbhavi; contact page) | J19: Domestic | K19: 4 | L19: https://probots.co.in/2-pin-fixed-screw-terminal-block-connector-5-08mm.html | N19: Listed Rs 15.00 incl GST. In stock. | O19: Product page | P19: 2026-10-24 | Q19: 0 | R19: 0
A20: Lane Controller PCB | B20: Buzzer | C20: Piezo buzzer B-27, 3-24V continuous | D20: 1 | E20: 49 | F20: =IF(ISNUMBER(E20),D20*E20,0) -> 49 | H20: Probots (Probots Technologies) | I20: Bengaluru (Nagarbhavi; contact page) | J20: Domestic | K20: 4 | L20: https://probots.co.in/piezo-electric-buzzer-alarm-3v-24v-continuous-b27.html | N20: Listed Rs 49.00 incl GST. Price seen on Probots listing grid. | O20: Store/category listing page | P20: 2026-10-24 | Q20: 0 | R20: 0
A21: Lane Controller PCB | B21: Status RGB LED | C21: WS2812 12-LED ring board | D21: 1 | E21: 149 | F21: =IF(ISNUMBER(E21),D21*E21,0) -> 149 | H21: Probots (Probots Technologies) | I21: Bengaluru (Nagarbhavi; contact page) | J21: Domestic | K21: 4 | L21: https://probots.co.in/rgb-led-12-bit-ws2812-circular-development-board.html | N21: Listed Rs 149.00 incl GST. In stock. | O21: Product page | P21: 2026-10-24 | Q21: 0 | R21: 0
A22: Lane Controller PCB | B22: PCB fabrication | C22: 2-layer FR4 ~100x80 mm, 5 pcs (1 lot) | D22: 1 | E22: 942.82 | F22: =IF(ISNUMBER(E22),D22*E22,0) -> 942.82 | H22: LionCircuits | I22: Bengaluru (080 phone; Karnataka facility) - address not on site, confirm | J22: Domestic | K22: 9 | L22: https://lioncircuits.com/ | M22: Quote also from another Bengaluru/Delhi fab | N22: Listed Rs 799.00; GST not stated, +18% applied (conservative). Advertised '5 boards for Rs 799 in 5-6 days'. Final price depends on size/spec quote. Lead time = 5-6 days + about 3 days shipping. | O22: Vendor homepage offer | P22: 2026-10-24 | Q22: 0 | R22: 0
A23: Lane Controller PCB | B23: Misc passives & connectors | C23: R/C 0805, electrolytics, ferrites, SMBJ33A on 24V, headers, JST, RJ45/RS485 connector, polyfuse | D23: 1 | E23: quote needed | F23: =IF(ISNUMBER(E23),D23*E23,0) -> 0 | G23: 800-1,500 (line) | H23: LionCircuits | I23: Bengaluru (080 phone; Karnataka facility) - address not on site, confirm | J23: Domestic | K23: 10 | L23: https://lioncircuits.com/ | M23: Probots | N23: Quote needed. One lot. Now also covers: 470 uF 50 V low-ESR + SMCJ28A at the IBT-2 module terminals, 1x8 2.54 mm header for J14, 2x SM712-class TVS spares, ferrites, JST-XH, RJ45/Cat6 (see spec). Range unchanged from 24 Oct: re-quote. | O23: ESTIMATE - quote needed | P23: 2026-10-24 | Q23: 800 | R23: 1500
A24: Lane Controller PCB | B24: Schematic parts not otherwise listed | C24: TI THVD1450DR RS485 (replaces MAX3485ESA); TPS54560BDDA 5 A buck + 6.8 uH inductor + B560C + FQD11P06 reverse-polarity FET (replaces XL4015 on the PCB); TLV62569DBVR 3.3 V buck + 2.2 uH (replaces AP2112K); TPS3823-33DBVR watchdog; 3x 74AHCT1G08 (U9, U10, U19); SN74HCT245PWR; USBLC6-2SC6; GCT USB4105 USB-C; 2x 2N7002; 2x IRLML0060; BAT54/SS14/S1M/1N4148W diodes; 3 A nano fuse + MF-R075 polyfuse | D24: 1 | E24: quote needed | F24: =IF(ISNUMBER(E24),D24*E24,0) -> 0 | G24: 2,500-5,000 (line) | H24: LionCircuits | I24: Bengaluru (080 phone; Karnataka facility) - address not on site, confirm | J24: Domestic | K24: 10 | M24: LCSC-type parts are not an allowed source (non-Indian); Robocraze/Probots for modules only | N24: ESTIMATE added 25 Oct. ESDS section 11 item 2: the BOM listed MAX3485ESA, XL4015 and AP2112K while the schematic uses other parts. These schematic-only parts have no vendor page opened. The range is a placeholder sized from the three superseded lines (Rs 2,712 priced) plus about 25 small parts; get a LionCircuits (or Delhi/Bengaluru distributor) quote against the generated netlist before ordering. | O24: ESTIMATE - quote needed | P24: 2026-10-25 | Q24: 2500 | R24: 5000
A25: Lane Controller PCB | B25: SUBTOTAL - Lane Controller PCB | F25: =SUM(F12:F24) -> 4476.54 | K25: =MAX(K12:K24) -> 10 | Q25: =SUM(Q12:Q24) -> 3300 | R25: =SUM(R12:R24) -> 6500
A27: UHF RFID Reader | B27: UHF integrated reader | C27: ID Tech IDT 85 mid-range UHF reader, 865-867 MHz, up to 8 m. IndustryBuying lists Wiegand + RS232 only; TradeIndia lists RS232/RS485/TCP-IP/Wiegand 26/34 and IP65. RS485, IP rating and EPC Gen2 to be confirmed in writing | D27: 1 | E27: 25959 | F27: =IF(ISNUMBER(E27),D27*E27,0) -> 25959 | H27: ID Tech Solutions Pvt Ltd (OEM); price ref. IndustryBuying | I27: Gurugram (Plot 610, Udyog Vihar Ph V; TradeIndia) | J27: Local-Delhi NCR | K27: 6 | L27: https://www.industrybuying.com/card-reader-id-tech-ITE.CAR.38552208 | M27: Eco Track Systems, New Delhi: 'RFID Integrated Reader 6 Meters' Rs 10,000 (GST n/s; interfaces not listed; the seller's page gives the UHF band as 865-928 MHz, so India-band compliance is unconfirmed) https://m.indiamart.com/ecotracksystems/integrated-reader.html | N27: Listed Rs 25,959.00 incl GST. 'Ships within 3 days' (stated). OEM's TradeIndia listing shows about Rs 14,000 (approx), so a direct quote may cut this line by about 45%. 25-Oct re-check of the IndustryBuying page: price Rs 25,959 unchanged; interfaces Wiegand + RS232 (no RS485); IP rating not listed; 9 V DC supply; -10 to 50 C operating temperature; RF output up to 30 dBm adjustable; fixed-frequency emission mode within 865-867 MHz. Ask ID Tech for: RS485 variant, WPC ETA certificate, India channel plan (865.7/866.3/866.9/867.5 MHz under G.S.R. 853(E)) and how e.r.p. is kept at or below 2 W with the built-in antenna. | O27: Product page | P27: 2026-10-25 | Q27: 0 | R27: 0
A28: UHF RFID Reader | B28: UHF test tags | C28: UHF RFID windshield tags (bench tests; the live demo uses a real FASTag) | D28: 10 | E28: 14.16 | F28: =IF(ISNUMBER(E28),D28*E28,0) -> 141.6 | H28: Eco Track Systems | I28: New Delhi (IndiaMART profile, GST 07AAFFE8904J2Z8) | J28: Local-Delhi NCR | K28: 3 | L28: https://m.indiamart.com/ecotracksystems/profile.html | N28: Listed Rs 12.00; GST not stated, +18% applied (conservative). Listed per piece on IndiaMART profile as 'RFID Windshield Tag' (UHF/EPC Gen2 not stated on the page): confirm UHF 865-867 MHz EPC Gen2 before buying. | O28: Store/category listing page | P28: 2026-10-25 | Q28: 0 | R28: 0
A29: UHF RFID Reader | B29: SUBTOTAL - UHF RFID Reader | F29: =SUM(F27:F28) -> 26100.6 | K29: =MAX(K27:K28) -> 6 | Q29: =SUM(Q27:Q28) -> 0 | R29: =SUM(R27:R28) -> 0
A31: ANPR Camera | B31: ANPR camera 2MP IR | C31: CP Plus CP-UNC-TD21ZL6C-VMDS 2MP bullet, 2.7-13.5mm motorized, 120dB WDR, 60m IR, IP67 | D31: 1 | E31: 4071 | F31: =IF(ISNUMBER(E31),D31*E31,0) -> 4071 | H31: Secure Bazaar (IndiaMART) | I31: Chennai (ships from Chennai) | J31: Domestic | K31: 7 | L31: https://m.indiamart.com/proddetail/cp-plus-cp-unc-td21zl6c-vmds-bullet-camera-2854862398948.html | M31: Deot International, New Delhi: Hikvision DS-2CD1023G0E-I 2MP IR fixed bullet Rs 3,350 excl GST (Rs 3,953) https://m.indiamart.com/proddetail/hikvision-ds-2cd1023g0e-i-2-mp-ir-fixed-network-bullet-camera-22509971212.html | N31: Listed Rs 3,450.00 excl GST; +18% GST applied. 25-Oct re-check: price Rs 3,450 excl GST unchanged, in stock, seller Secure Bazaar, Chennai. The spec table says 'Analog Camera' although the title says Network Camera. PoE, ONVIF/RTSP and the IR wavelength (850 nm required) are NOT stated; shutter is listed as 1/100000 s (implausible, treat as maximum). Get written confirmation of PoE, RTSP and 850 nm IR before payment; if 12V-only, add a PoE splitter. | O31: Product page | P31: 2026-10-25 | Q31: 0 | R31: 0
A32: ANPR Camera | B32: SUBTOTAL - ANPR Camera | F32: =SUM(F31:F31) -> 4071 | K32: =MAX(K31:K31) -> 7 | Q32: =SUM(Q31:Q31) -> 0 | R32: =SUM(R31:R31) -> 0
A34: PoE Switch | B34: PoE switch | C34: Netgear GS305P 5-port Gigabit unmanaged PoE | D34: 1 | E34: 5310 | F34: =IF(ISNUMBER(E34),D34*E34,0) -> 5310 | H34: Accruepole Pvt Ltd (IndiaMART) | I34: Mumbai (Kandivali East; ships from Mumbai) | J34: Domestic | K34: 7 | L34: https://m.indiamart.com/proddetail/5-port-gigabit-ethernet-poe-unmanaged-switch-gs305p-netgear-2856793072391.html | M34: Gigalink Technologies, Mumbai (Andheri E): Netgear 8-port, 4xPoE 53W Rs 4,200 excl GST https://m.indiamart.com/proddetail/8-port-gigabit-ethernet-plus-with-4-ports-poe-53w-24243207948.html ; PrimeABGB, Lamington Rd Mumbai: Cadyce CA-PS800 Rs 4,118 | N34: Listed Rs 4,500.00 excl GST; +18% GST applied. PoE budget and input voltage not on listing (the box includes its own DC adapter, so this switch runs from mains through its adapter, not from the 12 V rail): confirm budget >= camera + spare. The alt listing's model name is inconsistent (GS308PP vs GS108PE). | O34: Product page | P34: 2026-10-25 | Q34: 0 | R34: 0
A35: PoE Switch | B35: SUBTOTAL - PoE Switch | F35: =SUM(F34:F34) -> 5310 | K35: =MAX(K34:K34) -> 7 | Q35: =SUM(Q34:Q34) -> 0 | R35: =SUM(R34:R34) -> 0
A37: Occupancy Nodes x4 | B37: Node MCU | C37: ESP32-C3 SuperMini (RISC-V, USB-C) | D37: 4 | E37: 242 | F37: =IF(ISNUMBER(E37),D37*E37,0) -> 968 | H37: Probots (Probots Technologies) | I37: Bengaluru (Nagarbhavi; contact page) | J37: Domestic | K37: 4 | L37: https://probots.co.in/esp32-c3-supermini-wifi-bluetooth-development-board-32-bit-risc-v-uart-i2c-spi.html | M37: Probots ESP32-C3-Mini-1 dual USB-C board Rs 999 | N37: Listed Rs 242.00 incl GST. Page shows in stock, but metadata says OOS: confirm. | O37: Product page | P37: 2026-10-25 | Q37: 0 | R37: 0
A38: Occupancy Nodes x4 | B38: Distance sensor | C38: VL53L1X ToF laser ranging module (up to 4 m) | D38: 4 | E38: 799 | F38: =IF(ISNUMBER(E38),D38*E38,0) -> 3196 | H38: Probots (Probots Technologies) | I38: Bengaluru (Nagarbhavi; contact page) | J38: Domestic | K38: 14 | L38: https://probots.co.in/vl53l1x-tof-laser-ranging-sensor-module.html | M38: Thingbits, Mumbai: DFRobot A02YYUW waterproof ultrasonic Rs 1,698.02 incl GST (SOLD OUT) https://thingbits.in/products/a02yyuw-waterproof-ultrasonic-sensor | N38: Listed Rs 799.00 incl GST. OUT OF STOCK 24-Oct: 14-day lead time is an assumption. Two other Probots VL53L1X listings exist (unpriced). | O38: Product page | P38: 2026-10-25 | Q38: 0 | R38: 0
A39: Occupancy Nodes x4 | B39: Bay LED | C39: WS2812 12-LED ring | D39: 4 | E39: 149 | F39: =IF(ISNUMBER(E39),D39*E39,0) -> 596 | H39: Probots (Probots Technologies) | I39: Bengaluru (Nagarbhavi; contact page) | J39: Domestic | K39: 4 | L39: https://probots.co.in/rgb-led-12-bit-ws2812-circular-development-board.html | N39: Listed Rs 149.00 incl GST. In stock. | O39: Product page | P39: 2026-10-24 | Q39: 0 | R39: 0
A40: Occupancy Nodes x4 | B40: Node 5V supply | C40: 5V 2A USB adapter + cable per node | D40: 4 | E40: quote needed | F40: =IF(ISNUMBER(E40),D40*E40,0) -> 0 | G40: 800-1,400 (line) | H40: Local market (Delhi NCR) | I40: Delhi NCR | J40: Local-Delhi NCR | K40: 3 | N40: Not priced: quote needed (about Rs 200-350 each). | O40: ESTIMATE - quote needed | P40: 2026-10-24 | Q40: 800 | R40: 1400
A41: Occupancy Nodes x4 | B41: SUBTOTAL - Occupancy Nodes x4 | F41: =SUM(F37:F40) -> 4760 | K41: =MAX(K37:K40) -> 14 | Q41: =SUM(Q37:Q40) -> 800 | R41: =SUM(R37:R40) -> 1400
A43: P10 LED Sign | B43: P10 outdoor LED module | C43: P10 red SMD outdoor module 320x160 mm, 32x16, HUB12 | D43: 1 | E43: 699 | F43: =IF(ISNUMBER(E43),D43*E43,0) -> 699 | H43: Probots (Probots Technologies) | I43: Bengaluru (Nagarbhavi; contact page) | J43: Domestic | K43: 14 | L43: https://probots.co.in/p10-red-smd-outdoor-led-display-module-160x320mm.html | M43: Pixel Led Pvt Ltd, Navi Mumbai (Airoli): outdoor P10 red Rs 340 excl GST (Rs 401.20) https://m.indiamart.com/proddetail/outdoor-p10-red-led-display-module-21357608312.html | N43: Listed Rs 699.00 incl GST. OUT OF STOCK 24-Oct, so the alt vendor (1-week delivery stated) is the likely buy. | O43: Product page | P43: 2026-10-25 | Q43: 0 | R43: 0
A44: P10 LED Sign | B44: P10 controller (fallback) | C44: Huidu HD-W00 single-colour Wi-Fi LED controller | D44: 1 | E44: 538 | F44: =IF(ISNUMBER(E44),D44*E44,0) -> 538 | H44: Probots (Probots Technologies) | I44: Bengaluru (Nagarbhavi; contact page) | J44: Domestic | K44: 14 | L44: https://probots.co.in/w00-led-display-single-colour-wifi-controller-card-hd.html | M44: Quote: Nehru Place LED dealers | N44: Listed Rs 538.00 incl GST. OUT OF STOCK. The primary drive is HUB12 from the Lane PCB; this card is a fallback. | O44: Product page | P44: 2026-10-24 | Q44: 0 | R44: 0
A45: P10 LED Sign | B45: P10 5V supply | C45: XL4015 24V->5V buck, 5A max | D45: 1 | E45: 299 | F45: =IF(ISNUMBER(E45),D45*E45,0) -> 299 | H45: Probots (Probots Technologies) | I45: Bengaluru (Nagarbhavi; contact page) | J45: Domestic | K45: 4 | L45: https://probots.co.in/xl4015-step-down-buck-converter-adjustable-max-output-36v-5a.html | N45: Listed Rs 299.00 incl GST. In stock. | O45: Product page | P45: 2026-10-25 | Q45: 0 | R45: 0
A46: P10 LED Sign | B46: SUBTOTAL - P10 LED Sign | F46: =SUM(F43:F45) -> 1536 | K46: =MAX(K43:K45) -> 14 | Q46: =SUM(Q43:Q45) -> 0 | R46: =SUM(R43:R45) -> 0
A48: Barrier Drive | B48: 24V geared DC motor | C48: Lucas TVS wiper motor assembly 24V, 18 Nm (model 26971117A), worm-geared | D48: 1 | E48: 944 | F48: =IF(ISNUMBER(E48),D48*E48,0) -> 944 | H48: Moglix (Lucas TVS packer: Shahdara, New Delhi) | I48: New Delhi (packer address) - Moglix dispatch city not verified | J48: Local-Delhi NCR | K48: 7 | L48: https://www.moglix.com/lucas-tvs-wiper-motor-assembly-24-v-18-nm-for-hindustan-72-71b-front-end-loader-front-screentriv-luc-tsrxs6/mp/msnl5gln362yk4 | M48: Probots, Bengaluru: 6280 24V 30rpm reversible worm, self-locking, 48 kg-cm (~4.7 Nm) Rs 9,999 incl GST, in stock https://probots.co.in/6280-24v-30rpm-reversible-worm-gear-high-torque-self-locking-motor-left.html | N48: Listed Rs 944.00 incl GST. 'AVAILABLE ON REQUEST' (stock not confirmed; dispatch city still not shown). RPM, rated vs stall torque, duty, stall current and self-locking are NOT listed. DECISION 25 Oct (cad/calcs/CALCS.md section 4): accepted as a DEMO motor only. The requirement is 11.6 N.m at a 15 m/s operating wind (margin 1.56), so the demo rule is: move the boom only in wind <= 12 m/s (margin 2.2). Still-air requirement 2.1 N.m. Self-locking is NOT assumed; storm survival (93 N.m raised-boom gust) is carried by a storm-lock pin, not by this gearbox. A 15 m/s / production rating needs a >= 30 N.m self-locking gearmotor with a datasheet (not found at an allowed seller; the Probots 6280 and 5840 worm motors are 4.4-35 kg.cm; see docs/OPEN_DECISIONS.md D1). The 5840-31ZY page (Rs 1,799, 45 kg.cm, 10 rpm, out of stock) is 4.4 N.m and far below the need. | O48: Product page | P48: 2026-10-25 | Q48: 0 | R48: 0
A49: Barrier Drive | B49: Limit switches | C49: ME-8108 rotary adjustable roller limit switch | D49: 2 | E49: 399 | F49: =IF(ISNUMBER(E49),D49*E49,0) -> 798 | H49: Probots (Probots Technologies) | I49: Bengaluru (Nagarbhavi; contact page) | J49: Domestic | K49: 4 | L49: https://probots.co.in/rotary-adjustable-roller-micro-limit-switch-me-8108.html | M49: Probots micro limit roller switch Rs 69 (OOS) | N49: Listed Rs 399.00 incl GST. In stock. Positions: 0 deg and 90 deg. 25 Oct decision: these roller switches (NC contact between +24V_FIELD and the input) are the limit sensors; the M12 inductive sensors in MATERIALS are dropped. | O49: Product page | P49: 2026-10-25 | Q49: 0 | R49: 0
A50: Barrier Drive | B50: IR photo-beam pair | C50: Delta 18mm through-beam photoelectric (PS-MT5 series), 10-30VDC, PNP NO, 5-10 m | D50: 2 | E50: 2120.46 | F50: =IF(ISNUMBER(E50),D50*E50,0) -> 4240.92 | H50: SBM Electric Techno Pvt Ltd (IndiaMART) | I50: Gurugram (ships from Gurugram) | J50: Local-Delhi NCR | K50: 3 | L50: https://m.indiamart.com/proddetail/ps-mt5-usb2-delta-18mm-thru-beam-gkdp-18-3a30-pc-my3n-j-24vdc-my3n-j-12vdc-my3n-j-110vac-pyf11a-e-26029950830.html | M50: Pioneer Enterprises, New Delhi: boom-barrier photocell 12-24VDC 20 m Rs 3,500 excl GST https://m.indiamart.com/proddetail/boom-barrier-photocell-sensor-2853343495312.html | N50: Listed Rs 1,797.00 excl GST; +18% GST applied. Qty 2 = emitter + receiver priced per piece (conservative). Confirm whether the price covers a pair. 25-Oct: listing title mixes several models, brand field says Omron, and sensing distance is given as both 1 m and 5-10 m; it has no EN 12978 / self-test claim. 25 Oct: the PNP output is now compatible, because the schematic input was changed to active-high (24 V on the terminal = beam clear = LED on). Required receiver mode: light-ON (output driven while the beam is clear) so a cut wire or lost supply reads as blocked; confirm on the part. | O50: Product page | P50: 2026-10-25 | Q50: 0 | R50: 0
A51: Barrier Drive | B51: E-stop | C51: ProMax 22mm emergency-stop mushroom, metal, 2-pole (listing says 'waterproof'; IP rating not stated) | D51: 1 | E51: 899 | F51: =IF(ISNUMBER(E51),D51*E51,0) -> 899 | H51: Probots (Probots Technologies) | I51: Bengaluru (Nagarbhavi; contact page) | J51: Domestic | K51: 4 | L51: https://probots.co.in/promax-22mm-emergency-stop-switch-mushroom-head-waterproof-metal-2-pole.html | N51: Listed Rs 899.00 incl GST. Rated 1A DC (listing is inconsistent: 3 A / 10 A elsewhere on the page): it breaks the motor-relay coil / driver enable, not motor current directly. 25 Oct: now actually in the coil loop of the contactor K1 below (contacts rated 1 A DC; coil current about 0.2 A assumed, to be confirmed). | O51: Product page | P51: 2026-10-25 | Q51: 0 | R51: 0
A52: Barrier Drive | B52: Motor power contactor K1 | C52: Schneider Electric LC1D09BD, 3-pole TeSys D contactor, 24 VDC coil (E-stop in the coil loop; wire the three power poles in series in the +24 V motor line) | D52: 1 | E52: 1226.02 | F52: =IF(ISNUMBER(E52),D52*E52,0) -> 1226.02 | H52: Prem Associates (IndiaMART) | I52: New Delhi | J52: Local-Delhi NCR | K52: 3 | L52: https://m.indiamart.com/proddetail/schneider-lc1d09bd-power-contactors-23214488912.html | M52: Industricals, Mumbai: LC1D09BD Rs 1,950 excl GST https://m.indiamart.com/proddetail/schneider-9-24a-3-pole-440v-dc-contactor-lc1d09bd-18744546455.html | N52: Listed Rs 1,039.00 excluding all taxes (seller GST-registered); +18% GST applied = Rs 1,226.02. Replaces the Rs 299 24 V relay module (PRO4603), which could not implement the E-stop coil loop (ESDS section 11 item 3). Coil power and DC-3/DC-5 contact rating are NOT on the listing: confirm on the Schneider datasheet (assumed 0.2 A coil hold, 24 V; 5 A inductive motor load across series poles). Prices and stock are not confirmed with the seller. | O52: Store/category listing page | P52: 2026-10-25 | Q52: 0 | R52: 0
A53: Barrier Drive | B53: Presence sensor under boom (inductive loop detector) | C53: Single-channel inductive loop detector PD132, 230 V AC 50 Hz, relay output (SAFETY F4 secondary protection); loop wire laid in the wiring line | D53: 1 | E53: 2124 | F53: =IF(ISNUMBER(E53),D53*E53,0) -> 2124 | H53: Golf Automation Solutions Pvt Ltd (IndiaMART) | I53: Noida | J53: Local-Delhi NCR | K53: 3 | L53: https://m.indiamart.com/proddetail/loop-detector-pd132-2851226164712.html | M53: Bharat Trade Automation, Ghaziabad: single/dual channel loop detector Rs 2,000 excl GST https://m.indiamart.com/proddetail/vehicle-loop-detector-dual-channel-21612227255.html | N53: Listed Rs 1,800 excluding all taxes (unit not stated; seller GST-registered); +18% GST = Rs 2,124.00. Supply 230 V AC, relay output rating NOT stated: wire its dry contact between +24V_FIELD and the PRESENCE input (J5.6), and confirm the contact rating. The loop wire (about 10 m of 1.5 sq mm) and a saw-cut are in the wiring estimate. Under EN 12978 an inductive loop is outside scope, so it stays secondary protection beside the through-beam pair. | O53: Store/category listing page | P53: 2026-10-25 | Q53: 0 | R53: 0
A54: Barrier Drive | B54: Flange bearings UCFL204 x2 | C54: UCFL204 oval 2-bolt flange bearing unit, 20 mm bore, 2 off (MATERIALS section c, stub shaft support) | D54: 2 | E54: 236 | F54: =IF(ISNUMBER(E54),D54*E54,0) -> 472 | H54: Arihant Enterprises (IndiaMART) | I54: Chennai | J54: Domestic | K54: 5 | L54: https://m.indiamart.com/proddetail/ucfl204-flange-block-bearing-20588331712.html | M54: A.J. Traders, Mumbai: JSN UCFL204 Rs 115 excl GST (bore 20-40 mm range listed) https://m.indiamart.com/proddetail/ucfl-pillow-block-bearings-ucfl204-20568146348.html | N54: Listed Rs 200 excluding all taxes per piece (brands BXY/NTN/FAG/TR listed together; bore 20 mm); +18% GST = Rs 236.00. Brand and quality are not guaranteed by a listing: ask for a branded unit if the budget allows. | O54: Store/category listing page | P54: 2026-10-25 | Q54: 0 | R54: 0
A55: Barrier Drive | B55: Barrier drive-train machined parts | C55: Ø20 EN8 stub shaft + 6 mm key, Ø70 6061 hub with tongue, 2x 5 mm carrier plates, bearing plate, M8 shoulder bolt, jaw coupling (MATERIALS section c) | D55: 1 | E55: quote needed | F55: =IF(ISNUMBER(E55),D55*E55,0) -> 0 | G55: 1,500-3,500 (line) | H55: Delhi NCR machine shop (to be named) | I55: Delhi NCR | J55: Local-Delhi NCR | K55: 7 | M55: Reliable Laser Works (Faridabad) for the plates | N55: ESTIMATE (no vendor page): about 1.4 kg of 6061 and EN8 (STEP: stub shaft 0.39, hub 0.27, carrier 0.31, bearing plate 0.41 kg) at the Rs 318.6/kg aluminium listing price plus turning/milling/laser allowance. Quote from a machine shop. | O55: ESTIMATE - quote needed | P55: 2026-10-25 | Q55: 1500 | R55: 3500
A56: Barrier Drive | B56: Storm-lock pin + manual-release pin | C56: Ø10 hardened MS storm-lock pin (boom hub to frame, 93 N.m survival gust) and a lanyarded quick-release pin to disconnect the boom by hand after a power loss | D56: 1 | E56: quote needed | F56: =IF(ISNUMBER(E56),D56*E56,0) -> 0 | G56: 200-600 (line) | H56: Local hardware (Delhi NCR) | I56: Delhi NCR | J56: Local-Delhi NCR | K56: 3 | N56: ESTIMATE added 25 Oct (no vendor page). Replaces the unpriced '24 V backup for fail-open' GAP: the baseline mains-loss behaviour is fail-in-place with a hand release (docs/OPEN_DECISIONS.md D2). Not yet in the CAD. | O56: ESTIMATE - quote needed | P56: 2026-10-25 | Q56: 200 | R56: 600
A57: Barrier Drive | B57: SUBTOTAL - Barrier Drive | F57: =SUM(F48:F56) -> 10703.94 | K57: =MAX(K48:K56) -> 7 | Q57: =SUM(Q48:Q56) -> 1700 | R57: =SUM(R48:R56) -> 4100
A59: Power & Protection | B59: 24V SMPS | C59: Mean Well LRS-200-24 (24V 8.8A 211.2W) | D59: 1 | E59: 2499 | F59: =IF(ISNUMBER(E59),D59*E59,0) -> 2499 | H59: Probots (Probots Technologies) | I59: Bengaluru (Nagarbhavi; contact page) | J59: Domestic | K59: 4 | L59: https://probots.co.in/smps-metal-power-supply-24v-8-8a-211-2w-lrs-200-24-mean-well.html | M59: Mean Well LRS-150-24 (the earlier choice) Rs 1,699 at Probots; R and D Control Systems (IndiaMART) lists Mean Well SMPS https://m.indiamart.com/r-and-d-controlsystems/switch-mode-power-supply.html | N59: Listed Rs 2,499.00 incl GST (Rs 2,117.80 + 381.20 GST); in stock at Nagarabhavi, Bengaluru; warranty 7 days. Page also shows a conflicting 'More information' table (10-15 A, 200-300 W): the title and description say 8.8 A / 211.2 W. Replaces the LRS-150-24 (6.5 A) because the 24 V bus peak with a 6 A motor was 8.66 A (power_model.py). With the motor limited to 5 A in firmware the peak is 7.66 A = 87 % of 8.8 A (overload starts at 110 %). Convection cooled. Moves to the separate power box (CALCS section 5). Authorised-distributor status not verified. | O59: Product page | P59: 2026-10-25 | Q59: 0 | R59: 0
A60: Power & Protection | B60: 12V SMPS | C60: Mean Well LRS-100-12 (12V 8.5A 102W) | D60: 1 | E60: 1499 | F60: =IF(ISNUMBER(E60),D60*E60,0) -> 1499 | H60: Probots (Probots Technologies) | I60: Bengaluru (Nagarbhavi; contact page) | J60: Domestic | K60: 4 | L60: https://probots.co.in/mean-well-smps-12v-8-5a-102w-metal-power-supply-lrs-100-12.html | M60: Quote: R and D Control Systems, New Delhi | N60: Listed Rs 1,499.00 incl GST. In stock. Feeds the RFID reader, P10 controller and camera if not PoE. | O60: Product page | P60: 2026-10-25 | Q60: 0 | R60: 0
A61: Power & Protection | B61: MCB | C61: Schneider Acti9 xC60 A9N1P06C, 1P 6A C-curve | D61: 2 | E61: 161.66 | F61: =IF(ISNUMBER(E61),D61*E61,0) -> 323.32 | H61: L&T-SuFin (seller: SV Nexus Enterprises) | I61: NOT VERIFIED - seller city not shown | J61: Domestic | K61: 6 | L61: https://lntsufin.com/product/schneider-electric-acti9-xc60-a9n1p06c-single-pole-6-a-c-curve-mcb/17753-69 | M61: Buy over the counter at Bhagirath Palace / Lajpat Rai Market (Delhi) to satisfy the city rule: quote | N61: Listed Rs 161.66 incl GST. Price tier shown for 10-100 pcs (possible MOQ 10, worst case +Rs 1,293). Delivery 28-30 Oct stated. Seller city unverified: RULE-1 GAP. 25 Oct: sits downstream of the RCCB below in the power box; SAFETY.md says 2-pole MCB but this is 1P: use 1P+N or confirm which conductor is switched. | O61: Product page | P61: 2026-10-25 | Q61: 0 | R61: 0
A62: Power & Protection | B62: Fuse holders + fuses | C62: 5x20mm panel/inline fuse holders x4 + assorted glass fuses | D62: 1 | E62: quote needed | F62: =IF(ISNUMBER(E62),D62*E62,0) -> 0 | G62: 300-600 (line) | H62: Probots (Probots Technologies) | I62: Bengaluru (Nagarbhavi; contact page) | J62: Domestic | K62: 4 | L62: https://probots.co.in/inline-5x20mm-glass-fuse-holder-with-22-awg-lead-wires-25pcs-bag.html | M62: Delhi electrical market | N62: Product found but price not captured: quote needed. | O62: ESTIMATE - quote needed | P62: 2026-10-24 | Q62: 300 | R62: 600
A63: Power & Protection | B63: AC SPD | C63: Type 2 SPD 1P+N, 40 kA Imax, In 30 kA, rated voltage 320 V (Uc not listed), Up < 1.5 kV, DIN rail, MOV | D63: 1 | E63: 295 | F63: =IF(ISNUMBER(E63),D63*E63,0) -> 295 | H63: Samriddhi Industries (IndiaMART) | I63: New Delhi | J63: Local-Delhi NCR | K63: 3 | L63: https://m.indiamart.com/proddetail/surge-protection-device-2859297106848.html | M63: Quote: Delhi electrical market (OBO/Phoenix) | N63: Listed Rs 250.00 excl GST; +18% GST applied. Unbranded: request a datasheet/test certificate. | O63: Product page | P63: 2026-10-25 | Q63: 0 | R63: 0
A64: Power & Protection | B64: 12V mini DC UPS | C64: Enerva mini UPS 12V, 27.5 Wh (RFID reader / LED controller ride-through) | D64: 1 | E64: 1298 | F64: =IF(ISNUMBER(E64),D64*E64,0) -> 1298 | H64: Enervation Powertech Pvt Ltd (IndiaMART) | I64: Noida | J64: Local-Delhi NCR | K64: 3 | L64: https://m.indiamart.com/proddetail/mini-ups-for-wifi-router-25743173988.html | M64: Newtech Synergy Systems, Noida: mini UPS Rs 999 | N64: Listed Rs 1,100.00; GST not stated, +18% applied (conservative). Listing says 'excluding all taxes' (18% added). Chemistry (LiFePO4?) and max output current not stated: confirm >=1.5A at 12V. 27.5 Wh at 12 V cannot drive the 24 V barrier motor; the baseline is fail-in-place with a hand release, a 24 V buffer is optional (docs/OPEN_DECISIONS.md D2). | O64: Store/category listing page | P64: 2026-10-25 | Q64: 0 | R64: 0
A65: Power & Protection | B65: Wiring & cabling | C65: 1.5/0.75 sq mm flexible cable, 3x Cat6 patch, ferrules, lugs, heat-shrink, cable ties | D65: 1 | E65: quote needed | F65: =IF(ISNUMBER(E65),D65*E65,0) -> 0 | G65: 1,500-2,800 (line) | H65: Local market (Delhi NCR) | I65: Delhi NCR | J65: Local-Delhi NCR | K65: 3 | N65: Quote needed. | O65: ESTIMATE - quote needed | P65: 2026-10-24 | Q65: 1500 | R65: 2800
A66: Power & Protection | B66: Cable glands PG-9 | C66: PG-9 nickel-plated brass gland with PA66 insert | D66: 6 | E66: 132 | F66: =IF(ISNUMBER(E66),D66*E66,0) -> 792 | H66: Probots (Probots Technologies) | I66: Bengaluru (Nagarbhavi; contact page) | J66: Domestic | K66: 4 | L66: https://probots.co.in/nickel-plated-brass-metal-cable-gland-gland-size-pg-7.html | N66: Listed Rs 132.00 incl GST. PG-9 price from related items on the PG-7 page. | O66: Related-product listing on vendor page | P66: 2026-10-24 | Q66: 0 | R66: 0
A67: Power & Protection | B67: Cable glands PG-11 | C67: PG-11 nickel-plated brass gland | D67: 2 | E67: 180 | F67: =IF(ISNUMBER(E67),D67*E67,0) -> 360 | H67: Probots (Probots Technologies) | I67: Bengaluru (Nagarbhavi; contact page) | J67: Domestic | K67: 4 | L67: https://probots.co.in/nickel-plated-brass-metal-cable-gland-gland-size-pg-7.html | N67: Listed Rs 180.00 incl GST. Price from related items on the PG-7 page. | O67: Related-product listing on vendor page | P67: 2026-10-24 | Q67: 0 | R67: 0
A68: Power & Protection | B68: DIN rail + terminals | C68: 35mm DIN rail 0.5 m + 10x DIN terminal blocks + end stops | D68: 1 | E68: quote needed | F68: =IF(ISNUMBER(E68),D68*E68,0) -> 0 | G68: 400-900 (line) | H68: Local market (Delhi NCR) | I68: Delhi NCR | J68: Local-Delhi NCR | K68: 3 | N68: Quote needed. | O68: ESTIMATE - quote needed | P68: 2026-10-24 | Q68: 400 | R68: 900
A69: Power & Protection | B69: RCCB 30 mA | C69: Schneider 2-pole 25 A 30 mA RCCB, DIN rail (SAFETY F6), upstream of the two MCBs | D69: 1 | E69: 1062 | F69: =IF(ISNUMBER(E69),D69*E69,0) -> 1062 | H69: Trademinds (IndiaMART) | I69: Mumbai (Mulund West) | J69: Domestic | K69: 5 | L69: https://m.indiamart.com/proddetail/schneider-25a-double-pole-rccb-22533281697.html | M69: Schneider RCCB listings by other sellers: https://m.indiamart.com/proddetail/schneider-electric-rccb-18276234755.html | N69: Listed Rs 900 per piece excluding all taxes (30 mA, 2-pole, 25 A; seller GST-verified, rating 4.5/5 from 18 reviews); +18% GST = Rs 1,062.00. Model number not listed. | O69: Store/category listing page | P69: 2026-10-25 | Q69: 0 | R69: 0
A70: Power & Protection | B70: Bimetal thermostats 70/80 C | C70: KSD301-type NC bimetal thermostats, 70 C and 80 C, 10 A (SAFETY F7) | D70: 2 | E70: quote needed | F70: =IF(ISNUMBER(E70),D70*E70,0) -> 0 | G70: 150-400 (line) | H70: Delhi electronics market (seller to be named) | I70: Delhi NCR | J70: Local-Delhi NCR | K70: 3 | N70: ESTIMATE (no usable page): searched 25 Oct; KSD301-type NC 10 A units at 60-150 C exist on robu.in (Pune, rejected by the city rule) and on non-Indian sites. Quote 2 pcs (70 C and 80 C) from a Delhi electronics market. | O70: ESTIMATE - quote needed | P70: 2026-10-25 | Q70: 150 | R70: 400
A71: Power & Protection | B71: Power box (pole base, shaded) | C71: PVC IP65 hinged-door enclosure 250x190x95 mm for LRS-200-24, LRS-100-12, 2 MCBs, RCCB, SPD, mini UPS (moves 9.6 W out of the Edge box) | D71: 1 | E71: 295 | F71: =IF(ISNUMBER(E71),D71*E71,0) -> 295 | H71: Jenshri India Pvt Ltd (IndiaMART) | I71: New Delhi | J71: Local-Delhi NCR | K71: 3 | L71: https://m.indiamart.com/proddetail/250x190x95mm-outdoor-pole-box-2858984643197.html | M71: Hensel KG9003 217x253x115 (IP66) Rs 2,025, Vijay Kumar Sanjeev Kr Electric, New Delhi | N71: Listed Rs 250 per piece excluding all taxes (PVC, IP65, UV-resistant, hinged single door; seller GST-verified); +18% GST = Rs 295.00. WARNING: internal fit of the LRS-200-24 (about 99x97x30 mm), LRS-100-12, 3 DIN breakers and the SPD in 250x190x95 is not checked; a larger box may be needed (docs/OPEN_DECISIONS.md D6). Air temperature estimate 59.6 C at 45 C ambient (CALCS section 5). | O71: Product page | P71: 2026-10-25 | Q71: 0 | R71: 0
A72: Power & Protection | B72: SUBTOTAL - Power & Protection | F72: =SUM(F59:F71) -> 8423.32 | K72: =MAX(K59:K71) -> 6 | Q72: =SUM(Q59:Q71) -> 2350 | R72: =SUM(R59:R71) -> 4700
A74: Mechanical | B74: 80x80 Al T-slot extrusion (gantry pole) | C74: 8080 Slot 10 mm T-slot profile, 3 m (pole 2.4 m + cut margin); CALCS needs W >= 27 cm3, 8-slot, Al 6063 (T6 preferred); length in m | D74: 3 | E74: 2891 | F74: =IF(ISNUMBER(E74),D74*E74,0) -> 8673 | H74: Simplex Profilo Systems (IndiaMART) | I74: Gurugram (GST 06BMJPR6459N1Z5) | J74: Local-Delhi NCR | K74: 5 | L74: https://m.indiamart.com/simplexprofilosystems/aluminium-extrusion-profiles.html | M74: No other allowed-city 80x80 listing priced | N74: Listed Rs 2,450.00; GST not stated, +18% applied (conservative). 25-Oct: added because cad/calcs/CALCS.md section 1 shows 40x40 fails at Delhi design wind (FoS 0.46) and the pole is now 80x80. Listing shows '8080 Slot 10mm T Slot Aluminium Profile' at Rs 2,450/m (GST not stated, +18%); weight/m, section modulus and temper are NOT listed: get the drawing and confirm W >= 27 cm3 before ordering. Sold by the metre; confirm cut-to-length. | O74: Store/category listing page | P74: 2026-10-25 | Q74: 0 | R74: 0
A75: Mechanical | B75: 40x40 Al T-slot extrusion | C75: 4040 LIGHT T-slot profile, 1.2 kg/m (antenna arm 350 mm + camera arm 300 mm + spare; the pole is now 80x80, next line); length in m | D75: 1 | E75: 672.6 | F75: =IF(ISNUMBER(E75),D75*E75,0) -> 672.6 | H75: Simplex Profilo Systems (IndiaMART) | I75: Gurugram (GST 06BMJPR6459N1Z5) | J75: Local-Delhi NCR | K75: 5 | L75: https://m.indiamart.com/simplexprofilosystems/aluminium-extrusion-profiles.html | M75: Allied Technocare (IndiaMART Chennai): 40x40 Rs 850/m https://m.indiamart.com/proddetail/40x40-aluminium-extrusion-2856866587030.html | N75: Listed Rs 570.00; GST not stated, +18% applied (conservative). Price per metre. The 'Medium' 4040 is Rs 550/m (weight n/s). Qty cut from 3 m to 1 m on 25-Oct: 40x40 is used only for the two arms. | O75: Store/category listing page | P75: 2026-10-25 | Q75: 0 | R75: 0
A76: Mechanical | B76: 20x20 Al T-slot extrusion | C76: 2020 European-standard profile, 600 mm piece | D76: 2 | E76: 538 | F76: =IF(ISNUMBER(E76),D76*E76,0) -> 1076 | H76: Robocraze (TIF Labs Pvt Ltd) | I76: Bengaluru (Kalyan Nagar warehouse; contact page) | J76: Domestic | K76: 14 | L76: https://robocraze.com/products/600mm-2020-european-standard-aluminium-profile | M76: Quote: Simplex Profilo Systems, Gurugram | N76: Listed Rs 538.00 incl GST. SOLD OUT 24-Oct, so get the Gurugram quote. | O76: Product page | P76: 2026-10-25 | Q76: 0 | R76: 0
A77: Mechanical | B77: 4040 angle brackets | C77: DCBK 4040 die-cast Al angle bracket | D77: 8 | E77: 41.3 | F77: =IF(ISNUMBER(E77),D77*E77,0) -> 330.4 | H77: Simplex Profilo Systems (IndiaMART) | I77: Gurugram | J77: Local-Delhi NCR | K77: 5 | L77: https://m.indiamart.com/simplexprofilosystems/ | N77: Listed Rs 35.00; GST not stated, +18% applied (conservative). | O77: Store/category listing page | P77: 2026-10-24 | Q77: 0 | R77: 0
A78: Mechanical | B78: 2020 angle brackets | C78: DCBK 2020 die-cast Al angle bracket | D78: 6 | E78: 35.4 | F78: =IF(ISNUMBER(E78),D78*E78,0) -> 212.4 | H78: Simplex Profilo Systems (IndiaMART) | I78: Gurugram | J78: Local-Delhi NCR | K78: 5 | L78: https://m.indiamart.com/simplexprofilosystems/ | N78: Listed Rs 30.00; GST not stated, +18% applied (conservative). | O78: Store/category listing page | P78: 2026-10-24 | Q78: 0 | R78: 0
A79: Mechanical | B79: T-nuts | C79: Top-loading T-nut / hammer-head nut (slot size to confirm: 8 mm for 4040, 6 mm for 2020) | D79: 30 | E79: 21.24 | F79: =IF(ISNUMBER(E79),D79*E79,0) -> 637.2 | H79: Simplex Profilo Systems (IndiaMART) | I79: Gurugram | J79: Local-Delhi NCR | K79: 5 | L79: https://m.indiamart.com/simplexprofilosystems/ | N79: Listed Rs 18.00; GST not stated, +18% applied (conservative). | O79: Store/category listing page | P79: 2026-10-24 | Q79: 0 | R79: 0
A80: Mechanical | B80: Base plate (laser-cut) | C80: MS IS 2062 E250 plate 250x250x16 mm (per CALCS/MATERIALS, hot-dip galvanised), 4x D14 anchor holes on 190 mm PCD + socket location | D80: 1 | E80: quote needed | F80: =IF(ISNUMBER(E80),D80*E80,0) -> 0 | G80: 1,200-2,500 (line) | H80: Reliable Laser Works Pvt Ltd (IndiaMART) | I80: Faridabad | J80: Local-Delhi NCR | K80: 7 | L80: https://m.indiamart.com/proddetail/cnc-laser-cutting-service-2849776118462.html | M80: HB Engineering, Faridabad (Rs 15/min, Al up to 20 mm) | N80: Cutting listed Rs 30/sq ft (MS/SS/AL, up to 40 mm). Plate material + min-charge not listed: quote needed. 25-Oct: spec changed from Al 6061 10 mm to MS 16 mm to match CALCS (10 mm gives FoS 1.13); the Rs 1,200-2,500 range was set for the old plate and has not been re-estimated, re-quote and galvanising are open. | O80: ESTIMATE - quote needed | P80: 2026-10-24 | Q80: 1200 | R80: 2500
A81: Mechanical | B81: Gussets (laser-cut) | C81: 4x 6 mm MS gussets + 4x 6 mm MS socket cheeks (2 of 93x150, 2 of 81x150) per MATERIALS | D81: 1 | E81: quote needed | F81: =IF(ISNUMBER(E81),D81*E81,0) -> 0 | G81: 400-900 (line) | H81: Reliable Laser Works Pvt Ltd (IndiaMART) | I81: Faridabad | J81: Local-Delhi NCR | K81: 7 | L81: https://m.indiamart.com/proddetail/cnc-laser-cutting-service-2849776118462.html | N81: Same job as the base plate: quote needed. 25-Oct: now MS, and the 4 socket cheeks were missing from the BOM; the range has not been re-estimated. | O81: ESTIMATE - quote needed | P81: 2026-10-24 | Q81: 400 | R81: 900
A82: Mechanical | B82: Boom tube 60x30 Al | C82: Al rectangular tube 60x30 (about 1.5 mm wall), one stock length about 3.6 m, about 2.6 kg; qty in kg | D82: 2.6 | E82: 318.6 | F82: =IF(ISNUMBER(E82),D82*E82,0) -> 828.36 | H82: Gokal Chand Jagan Nath Nahar (IndiaMART) | I82: New Delhi | J82: Local-Delhi NCR | K82: 3 | L82: https://m.indiamart.com/proddetail/aluminum-rectangular-pipe-2406025197.html | M82: Gayatri Enterprises, New Delhi Rs 250/kg; Auto Tech Industry, Gurugram Rs 260/kg | N82: Listed Rs 270.00; GST not stated, +18% applied (conservative). Listed Rs/kg for a 2-inch section: confirm 60x30 availability. Only 1.2 m is needed; the kg figure is an estimate from section geometry. | O82: Store/category listing page | P82: 2026-10-25 | Q82: 0 | R82: 0
A83: Mechanical | B83: Edge enclosure IP65 | C83: GRASP IP65 modular enclosure 300x300x210 mm | D83: 1 | E83: 1834.9 | F83: =IF(ISNUMBER(E83),D83*E83,0) -> 1834.9 | H83: Super Electricals (IndiaMART) | I83: New Delhi | J83: Local-Delhi NCR | K83: 3 | L83: https://m.indiamart.com/proddetail/grasp-ip-65-modular-electrical-enclosures-7255097288.html | M83: No allowed-city 400x300x150 IP65 listing found (Idis India 400x300x150 Rs 1,050 is Ahmedabad: rejected) | N83: Listed Rs 1,555.00; GST not stated, +18% applied (conservative). DECISION 25 Oct: this bought 300x300x210 box is the design basis. Thermal result: box size is not the lever (0.6 K between 300x300x210 and 300x400x180, CALCS section 5); CAD/STEP/MATERIALS still model 300x400x180, so the DIN layout, heat-sink window and gasket drawing must be re-checked by the CAD owner (docs/OPEN_DECISIONS.md D6). No 400x300 size is listed at Super Electricals. | O83: Store/category listing page | P83: 2026-10-25 | Q83: 0 | R83: 0
A84: Mechanical | B84: PETG filament | C84: Anycubic PETG 1.75 mm 1 kg | D84: 2 | E84: 902 | F84: =IF(ISNUMBER(E84),D84*E84,0) -> 1804 | H84: Robocraze (TIF Labs Pvt Ltd) | I84: Bengaluru (Kalyan Nagar warehouse; contact page) | J84: Domestic | K84: 4 | L84: https://robocraze.com/search?q=petg+filament | M84: Moglix: eSUN PETG 1kg Rs 1,744 incl GST (available on request) | N84: Listed Rs 902.00 incl GST. For brackets, node housings, sign bezel. ASA not found at an allowed vendor: PETG used outdoors (UV risk). MATERIALS.md and CALCS assume ASA for the pole cap, cable boot, Pi tray, boom tip cap and occupancy nodes: either source ASA or accept PETG and change those documents. | O84: Store/category listing page | P84: 2026-10-24 | Q84: 0 | R84: 0
A85: Mechanical | B85: M3 fasteners | C85: M3 bolt+nut sets (20/25/40 mm) | D85: 50 | E85: 3 | F85: =IF(ISNUMBER(E85),D85*E85,0) -> 150 | H85: Probots (Probots Technologies) | I85: Bengaluru (Nagarbhavi; contact page) | J85: Domestic | K85: 4 | L85: https://probots.co.in/m3x25mm-bolts-and-nuts.html | N85: Listed Rs 3.00 incl GST. Price per set from Probots listing grid. | O85: Store/category listing page | P85: 2026-10-24 | Q85: 0 | R85: 0
A86: Mechanical | B86: Structural fasteners | C86: 4x M12 anchor bolts, M8/M6 SS bolts, washers, nyloc nuts | D86: 1 | E86: quote needed | F86: =IF(ISNUMBER(E86),D86*E86,0) -> 0 | G86: 800-1,600 (line) | H86: Delhi hardware market (seller to be named) | I86: Delhi NCR | J86: Local-Delhi NCR | K86: 2 | N86: Quote needed. | O86: ESTIMATE - quote needed | P86: 2026-10-24 | Q86: 800 | R86: 1600
A87: Mechanical | B87: Counterweight + shear pins | C87: MS counterweight 7 plates 100x60x10 (3.30 kg) + 5 mm 6061-T6 breakaway shear pins (spares) | D87: 1 | E87: quote needed | F87: =IF(ISNUMBER(E87),D87*E87,0) -> 0 | G87: 300-700 (line) | H87: Local fabricator (Delhi NCR) | I87: Delhi NCR | J87: Local-Delhi NCR | K87: 5 | N87: ESTIMATE (no vendor page). 7 MS plates 100x60x10 = 3.30 kg are the adopted counterweight (94 % balance; CALCS section 4) plus spare 5 mm 6061-T6 breakaway pins (the design gust loads the pin to 89 % of its break moment, so spares matter). Quote from a local fabricator. | O87: ESTIMATE - quote needed | P87: 2026-10-24 | Q87: 300 | R87: 700
A88: Mechanical | B88: Barrier housing | C88: MS base plate 360x310x8, 20x20 frame, 2 mm 5052 skins + 3 mm roof, powder coat (MATERIALS section c) | D88: 1 | E88: quote needed | F88: =IF(ISNUMBER(E88),D88*E88,0) -> 0 | G88: 5,000-9,000 (line) | H88: Reliable Laser Works Pvt Ltd (IndiaMART) | I88: Faridabad | J88: Local-Delhi NCR | K88: 7 | N88: ESTIMATE (no vendor page). STEP masses: 6.90 kg MS base plate, 2.71 kg Al frame, 5.43 kg skins/roof. Aluminium 8.1 kg x Rs 318.6/kg (boom-tube listing) = Rs 2,600, MS plate about Rs 600, laser/brake/weld/powder-coat allowance Rs 2,000-5,000. Quote from Reliable Laser Works (IndiaMART, Delhi NCR) or similar. | O88: ESTIMATE - quote needed | P88: 2026-10-25 | Q88: 5000 | R88: 9000
A89: Mechanical | B89: Edge heat sink + sun hood | C89: 200x150 extruded Al sink, 18 fins x 35 mm; 2 mm Al sun hood with 25 mm air gap; EPDM window gasket (CALCS section 5) | D89: 1 | E89: quote needed | F89: =IF(ISNUMBER(E89),D89*E89,0) -> 0 | G89: 2,000-4,500 (line) | H89: Delhi NCR heat-sink dealer + Reliable Laser Works, Faridabad | I89: Delhi NCR / Faridabad | J89: Local-Delhi NCR | K89: 7 | N89: ESTIMATE (no usable page): IndiaMART heat-sink pages found (Himalay Engineering, Mumbai: Rs 400/piece for an undimensioned sink; Marshah Electronics, Mumbai: extruded 6063-T5 with no price) do not state a 200x150 mm, 18-fin size. Sink 1.17 kg + sun hood 0.95 kg of Al plus cutting/bending. Quote. Without both the thermal prediction does not hold (CALCS section 5). | O89: ESTIMATE - quote needed | P89: 2026-10-25 | Q89: 2000 | R89: 4500
A90: Mechanical | B90: Vent + M25/M20/M16 glands | C90: ePTFE breather vent, nylon glands M25 x1, M20 x3, M16 x1 (MATERIALS section b) | D90: 1 | E90: quote needed | F90: =IF(ISNUMBER(E90),D90*E90,0) -> 0 | G90: 400-900 (line) | H90: Delhi electrical market (seller to be named) | I90: Delhi NCR | J90: Local-Delhi NCR | K90: 3 | N90: ESTIMATE (no vendor page opened for ePTFE vents or nylon glands from an allowed city). 1 vent + 5 glands. Quote. | O90: ESTIMATE - quote needed | P90: 2026-10-25 | Q90: 400 | R90: 900
A91: Mechanical | B91: Cable duct (38x38 substitute for 40x25) | C91: PVC cable duct 38x38 mm, 2 m pieces (cover not stated), 4 m for the pole run; the CAD duct is 40x25 | D91: 4 | E91: 53.1 | F91: =IF(ISNUMBER(E91),D91*E91,0) -> 212.4 | H91: AR Industries (IndiaMART) | I91: Noida | J91: Local-Delhi NCR | K91: 3 | L91: https://m.indiamart.com/proddetail/pvc-cable-duct-2859724144062.html | M91: Surana Enterprises, Bengaluru: 25 mm duct tray Rs 38/m https://m.indiamart.com/proddetail/pvc-cable-duct-tray-6719781833.html | N91: Listed Rs 45 per metre excluding all taxes, 2 m per piece (qty is metres); +18% GST = Rs 53.10/m. Size is 38x38, not the CAD 40x25; material, UV-stabilisation and cover are not stated. No 40x25 listing was found in the allowed cities. | O91: Store/category listing page | P91: 2026-10-25 | Q91: 0 | R91: 0
A92: Mechanical | B92: SUBTOTAL - Mechanical | F92: =SUM(F74:F91) -> 16431.26 | K92: =MAX(K74:K91) -> 14 | Q92: =SUM(Q74:Q91) -> 10100 | R92: =SUM(R74:R91) -> 20100
B94: Total of priced lines (verified vendor prices) | F94: =SUM(F10,F25,F29,F32,F35,F41,F46,F57,F72,F92) -> 124832.66
B95: Total of estimate lines - LOW (ESTIMATE) | F95: =SUM(Q10,Q25,Q29,Q32,Q35,Q41,Q46,Q57,Q72,Q92) -> 23349
B96: Total of estimate lines - HIGH (ESTIMATE) | F96: =SUM(R10,R25,R29,R32,R35,R41,R46,R57,R72,R92) -> 42299
B97: Base budget = priced + estimates HIGH | F97: =F94+F96 -> 167131.66
B98: Contingency 10% of base budget | F98: =ROUND(0.1*F97,2) -> 16713.17
B99: GRAND TOTAL (INR, incl GST) | F99: =F97+F98 -> 183844.83
B102: All prices INR incl. 18% GST (added where a page listed ex-GST or did not state GST). First checked 2026-10-24; vendor pages re-checked 2026-10-25 (see column P); new pages for the 25 Oct design update were checked 2026-10-25. Yellow cells = ESTIMATES, not vendor prices. After the 25 Oct review there are NO unpriced GAP lines left: each former GAP is either priced from a listing or carries a labelled estimate range. Lines with quantity 0 are superseded and kept for reference. Shipping not included.

Sheet Summary
A1: Subsystem | B1: Priced lines (INR) | C1: Estimate lines low (INR) | D1: Estimate lines high (INR) | E1: Budget = priced + est. high (INR) | F1: Max lead time (days) | G1: # lines | H1: # estimate lines | I1: # unpriced GAP lines (not in budget)
A2: Edge Node | B2: =BOM!F10 -> 43020 | C2: =BOM!Q10 -> 5099 | D2: =BOM!R10 -> 5499 | E2: =B2+D2 -> 48519 | F2: =BOM!K10 -> 7 | G2: 8 | H2: 2 | I2: 0
A3: Lane Controller PCB | B3: =BOM!F25 -> 4476.54 | C3: =BOM!Q25 -> 3300 | D3: =BOM!R25 -> 6500 | E3: =B3+D3 -> 10976.54 | F3: =BOM!K25 -> 10 | G3: 13 | H3: 2 | I3: 0
A4: UHF RFID Reader | B4: =BOM!F29 -> 26100.6 | C4: =BOM!Q29 -> 0 | D4: =BOM!R29 -> 0 | E4: =B4+D4 -> 26100.6 | F4: =BOM!K29 -> 6 | G4: 2 | H4: 0 | I4: 0
A5: ANPR Camera | B5: =BOM!F32 -> 4071 | C5: =BOM!Q32 -> 0 | D5: =BOM!R32 -> 0 | E5: =B5+D5 -> 4071 | F5: =BOM!K32 -> 7 | G5: 1 | H5: 0 | I5: 0
A6: PoE Switch | B6: =BOM!F35 -> 5310 | C6: =BOM!Q35 -> 0 | D6: =BOM!R35 -> 0 | E6: =B6+D6 -> 5310 | F6: =BOM!K35 -> 7 | G6: 1 | H6: 0 | I6: 0
A7: Occupancy Nodes x4 | B7: =BOM!F41 -> 4760 | C7: =BOM!Q41 -> 800 | D7: =BOM!R41 -> 1400 | E7: =B7+D7 -> 6160 | F7: =BOM!K41 -> 14 | G7: 4 | H7: 1 | I7: 0
A8: P10 LED Sign | B8: =BOM!F46 -> 1536 | C8: =BOM!Q46 -> 0 | D8: =BOM!R46 -> 0 | E8: =B8+D8 -> 1536 | F8: =BOM!K46 -> 14 | G8: 3 | H8: 0 | I8: 0
A9: Barrier Drive | B9: =BOM!F57 -> 10703.94 | C9: =BOM!Q57 -> 1700 | D9: =BOM!R57 -> 4100 | E9: =B9+D9 -> 14803.94 | F9: =BOM!K57 -> 7 | G9: 9 | H9: 2 | I9: 0
A10: Power & Protection | B10: =BOM!F72 -> 8423.32 | C10: =BOM!Q72 -> 2350 | D10: =BOM!R72 -> 4700 | E10: =B10+D10 -> 13123.32 | F10: =BOM!K72 -> 6 | G10: 13 | H10: 4 | I10: 0
A11: Mechanical | B11: =BOM!F92 -> 16431.26 | C11: =BOM!Q92 -> 10100 | D11: =BOM!R92 -> 20100 | E11: =B11+D11 -> 36531.26 | F11: =BOM!K92 -> 14 | G11: 18 | H11: 7 | I11: 0
A12: TOTAL | B12: =SUM(B2:B11) -> 124832.66 | C12: =SUM(C2:C11) -> 23349 | D12: =SUM(D2:D11) -> 42299 | E12: =SUM(E2:E11) -> 167131.66 | F12: =MAX(F2:F11) -> 14 | G12: =SUM(G2:G11) -> 72 | H12: =SUM(H2:H11) -> 18 | I12: =SUM(I2:I11) -> 0
A13: Contingency 10% | E13: =ROUND(0.1*E12,2) -> 16713.17
A14: GRAND TOTAL | E14: =E12+E13 -> 183844.83
A16: Cross-check: Summary GRAND TOTAL must equal BOM GRAND TOTAL -> | E16: =BOM!F99 -> 183844.83

Sheet Sources
A1: # | B1: URL | C1: Used for | D1: What it verified | E1: Checked on
A2: 1 | B2: https://probots.co.in/raspberry-pi-5-model-b-bcm2712-arm-cortex-a76-8gb-ram-2-4ghz-single-board-computer.html | C2: Edge Node: Raspberry Pi 5 8GB | D2: Product page | re-checked 25-Oct, see BOM notes | E2: 2026-10-25
A3: 2 | B3: https://probots.co.in/official-raspberry-pi-ai-hat-26-tops.html | C3: Edge Node: Raspberry Pi AI HAT+ 26 TOPS | D3: Product page | re-checked 25-Oct, see BOM notes | E3: 2026-10-25
A4: 3 | B4: https://probots.co.in/official-raspberry-pi-5-active-cooler-heatsink-fan.html | C4: Edge Node: Active cooler | D4: Product page | re-checked 25-Oct, see BOM notes | E4: 2026-10-25
A5: 4 | B5: https://robocraze.com/search?q=sandisk | C5: Edge Node: microSD card 128GB | D5: Store/category listing page | E5: 2026-10-24
A6: 5 | B6: https://probots.co.in/raspberry-pi-27w-usb-c-power-supply-white-in-plug.html | C6: Edge Node: USB-C PSU (bench / commissioning) | D6: Product page | re-checked 25-Oct, see BOM notes | E6: 2026-10-25
A7: 6 | B7: https://probots.co.in/xl4015-step-down-buck-converter-adjustable-max-output-36v-5a.html | C7: Edge Node: 24V->5.1V 5A buck (Pi 5 feed in enclosure) | D7: Product page | re-checked 25-Oct, see BOM notes | E7: 2026-10-25
A8: 7 | B8: https://probots.co.in/metal-case-raspberry-pi-5-x1202-ups-board.html | C8: Edge Node: Pi 5 UPS module (>=10 min ride-through) | D8: ESTIMATE - quote needed | re-checked 25-Oct, see BOM notes | E8: 2026-10-25
A9: 8 | B9: https://lioncircuits.com/parts/ESP32-S3-WROOM-1-N16R8 | C9: Lane Controller PCB: MCU module | D9: Product page | re-checked 25-Oct, see BOM notes | E9: 2026-10-25
A10: 9 | B10: https://lioncircuits.com/parts/MAX3485ESA+T | C10: Lane Controller PCB: RS485 transceiver | D10: Product page | E10: 2026-10-24
A11: 10 | B11: https://lioncircuits.com/parts/SM712.TCT | C11: Lane Controller PCB: RS485 TVS | D11: Product page | E11: 2026-10-24
A12: 11 | B12: https://probots.co.in/bts7960-43a-stepper-motor-driver-h-bridge-high-power-module-motor-control.html | C12: Lane Controller PCB: H-bridge motor driver | D12: Product page | re-checked 25-Oct, see BOM notes | E12: 2026-10-25
A13: 12 | B13: https://lioncircuits.com/parts/AP2112K-3.3TRG1 | C13: Lane Controller PCB: 3.3V regulator | D13: Product page | E13: 2026-10-24
... A90: 89 | B90: https://www.systeal.com/en/40-series-profiles/1433-aluminium-profile-10-mm-slot-80x80.html | C90: Pole mass reconciliation (non-Indian reference, not a purchase source) | D90: 80x80 10 mm slot: 4.45 kg/m, 1649 mm2, I = 130 cm4 | E90: 2026-10-25
